tq/__init__.py
tq/zip_file_reader.py
tq_zip_file_reader-1.0.dist-info/LICENSE
tq_zip_file_reader-1.0.dist-info/METADATA
tq_zip_file_reader-1.0.dist-info/WHEEL
tq_zip_file_reader-1.0.dist-info/top_level.txt
tq_zip_file_reader-1.0.dist-info/RECORD
